pkgstat/__init__.py
pkgstat/__main__.py
pkgstat/main.py
pkgstat-0.1.1.dist-info/entry_points.txt
pkgstat-0.1.1.dist-info/WHEEL
pkgstat-0.1.1.dist-info/METADATA
pkgstat-0.1.1.dist-info/RECORD
